go_annotation_changes.py
go_ontology_changes.py
go_refine_stats.py
go_reports.py
go_stats.py
obo_parser.py
go_stats-1.1.3.dist-info/LICENSE.txt
go_stats-1.1.3.dist-info/METADATA
go_stats-1.1.3.dist-info/WHEEL
go_stats-1.1.3.dist-info/top_level.txt
go_stats-1.1.3.dist-info/RECORD
