Metadata-Version: 2.1
Name: go-stats
Version: 1.1.3
Summary: Python Library to generate statistics on a Gene Ontology (GO) release
Home-page: https://github.com/geneontology/go-stats
Author: Laurent-Philippe Albou
Author-email: laurent.albou@lbl.gov
License: UNKNOWN
Keywords: GO,Gene Ontology,annotation,ontology,stats,changes,GOLR,statistics
Platform: UNKNOWN
Classifier: Programming Language :: Python :: 3
Classifier: Programming Language :: Python :: 3.6
Classifier: Programming Language :: Python :: 3.7
Classifier: License :: OSI Approved :: BSD License
Requires-Dist: requests
Requires-Dist: networkx
